Metadata-Version: 1.0
Name: emoji.py
Version: 0.1.0
Summary: Search emoji via command-line
Home-page: https://github.com/chenjiandongx/emoji.py
Author: chenjiandongx
Author-email: chenjiandongx@qq.com
License: MIT
Platform: UNKNOWN
